bandit_aws/__init__.py
bandit_aws/aws_checks.py
bandit_aws/test_aws_checks.py
bandit_aws-0.0.20200316120836.dist-info/METADATA
bandit_aws-0.0.20200316120836.dist-info/WHEEL
bandit_aws-0.0.20200316120836.dist-info/entry_points.txt
bandit_aws-0.0.20200316120836.dist-info/top_level.txt
bandit_aws-0.0.20200316120836.dist-info/RECORD
