Metadata-Version: 2.1
Name: bandit-aws
Version: 0.0.20200316120836
Summary: Bandit plugin to scan for AWS keys
Home-page: https://pypi.org/project/bandit-aws/
Author: CMCRC
Author-email: devcdt@cmcrc.com
License: GPLv3
Platform: UNKNOWN
Classifier: Programming Language :: Python :: 3
Classifier: Intended Audience :: Developers
Classifier: Operating System :: OS Independent
Classifier: License :: OSI Approved :: GNU General Public License v3 (GPLv3)
